[
  {
    "name": "Website Loka Baca",
    "desc": "Educational WordPress site offering informative articles for learning and growth.",
    "image": "lokabaca",
    "category": "basicweb",
    "links": {
      "view": "https://lokabaca.com",
      "code": "#"
    }
  },
  {
    "name": "Website SMKN 1 Kutasari",
    "desc": "Educational WordPress site offering informative articles for learning and growth.",
    "image": "smkn1kutasari",
    "category": "basicweb",
    "links": {
      "view": "https://smkn1kutasari.sch.id",
      "code": "#"
    }
  },{
    "name": "Ujian SMKN 1 Kutasari",
    "desc": "CodeIgniter-powered web app for efficient and secure exam administration.",
    "image": "ujian",
    "category": "basicweb",
    "links": {
      "view": "https://ujian.smkn1kutasari.sch.id",
      "code": "#"
    }
  },{
    "name": "SIAS SMKN 1 Kutasari",
    "desc": "CodeIgniter-based web app for streamlined school assistant management.",
    "image": "sias",
    "category": "basicweb",
    "links": {
      "view": "https://sias.smkn1kutasari.sch.id",
      "code": "#"
    }
  },{
    "name": "Simnilai SMKN 1 Kutasari",
    "desc": "CodeIgniter-powered web app for comprehensive student assessment and evaluation.",
    "image": "simnilai",
    "category": "basicweb",
    "links": {
      "view": "https://simnilai.smkn1kutasari.sch.id",
      "code": "#"
    }
  },{
    "name": "Merdeka SMKN 1 Kutasari",
    "desc": "Laravel-driven web app for holistic student assessment and evaluation.",
    "image": "merdeka",
    "category": "basicweb",
    "links": {
      "view": "https://km.smkn1kutasari.sch.id",
      "code": "#"
    }
  },{
    "name": "SSO SMKN 1 Kutasari",
    "desc": "Laravel-based web app for seamless SSO login experience.",
    "image": "sso",
    "category": "basicweb",
    "links": {
      "view": "https://sso.smkn1kutasari.sch.id",
      "code": "#"
    }
  },{
    "name": "Website Dzahin Hair",
    "desc": "WordPress website offering premium hair extensions for effortless style transformations.",
    "image": "dzahinhair",
    "category": "basicweb",
    "links": {
      "view": "https://www.dzahinhair.com",
      "code": "#"
    }
  },{
    "name": "Website Youty Hair Company",
    "desc": "WordPress website offering premium hair extensions for effortless style transformations.",
    "image": "youtyhaircompany",
    "category": "basicweb",
    "links": {
      "view": "https://www.youtyhaircompany.com",
      "code": "#"
    }
  }
]
